seashore/__init__.py
seashore/_version.py
seashore/executor.py
seashore/shell.py
seashore/tests/__init__.py
seashore/tests/test_executor.py
seashore/tests/test_shell.py
seashore-20.6.0.dist-info/LICENSE
seashore-20.6.0.dist-info/METADATA
seashore-20.6.0.dist-info/WHEEL
seashore-20.6.0.dist-info/top_level.txt
seashore-20.6.0.dist-info/RECORD
