Metadata-Version: 2.1
Name: seashore
Version: 20.6.0
Summary: A collection of shell abstractions
Home-page: http://github.com/shopkick/seashore
Maintainer: Shopkick
Maintainer-email: dev@shopkick.com
License: MIT
Platform: UNKNOWN
Requires-Dist: incremental
Requires-Dist: attrs (>=19.3.0)
Requires-Dist: singledispatch
